stemia/__init__.py
stemia/aretomo/__init__.py
stemia/aretomo/aln2xf.py
stemia/aretomo/batch.sh
stemia/cryosparc/__init__.py
stemia/cryosparc/fix_filament_ids.py
stemia/cryosparc/generate_tilt_angles.py
stemia/cryosparc/merge_defects_gainref.py
stemia/cryosparc/time_wasted.py
stemia/cryosparc/csplot/__init__.py
stemia/cryosparc/csplot/main.py
stemia/cryosparc/csplot/parse.py
stemia/cryosparc/csplot/plot.py
stemia/image/__init__.py
stemia/image/classify_densities.py
stemia/image/create_mask.py
stemia/image/extract_z_snapshots.py
stemia/image/flip_z.py
stemia/image/fourier_crop.py
stemia/image/project_profiles.py
stemia/image/rescale.py
stemia/image/center_filament/__init__.py
stemia/image/center_filament/center_filament.py
stemia/image/center_filament/funcs.py
stemia/imod/__init__.py
stemia/imod/find_NAD_params.py
stemia/relion/__init__.py
stemia/relion/align_filament_particles.py
stemia/relion/edit_star.py
stemia/utils/__init__.py
stemia/utils/click.py
stemia/utils/image_processing.py
stemia/utils/io_.py
stemia/warp/__init__.py
stemia/warp/fix_mdoc.py
stemia/warp/offset_angle.py
stemia/warp/parse_xml.py
stemia/warp/prepare_isonet.py
stemia/warp/preprocess_serialem.sh
stemia/warp/spoof_mdoc.py
stemia/warp/summarize.py
stemia-0.7.7.dist-info/METADATA
stemia-0.7.7.dist-info/WHEEL
stemia-0.7.7.dist-info/entry_points.txt
stemia-0.7.7.dist-info/licenses/LICENSE
stemia-0.7.7.dist-info/RECORD
