Metadata-Version: 2.3
Name: stemia
Version: 0.7.7
Summary: A personal collection of (sometimes...) useful scripts and tools for cryoem/cryoet.
Project-URL: homepage, https://github.com/brisvag/stemia
Project-URL: repository, https://github.com/brisvag/stemia
Author-email: Lorenzo Gaifas <brisvag@gmail.com>
License: GPLv3
License-File: LICENSE
Classifier: Development Status :: 3 - Alpha
Classifier: Intended Audience :: Science/Research
Classifier: License :: OSI Approved :: GNU General Public License v3 (GPLv3)
Classifier: Natural Language :: English
Classifier: Programming Language :: Python :: 3
Classifier: Programming Language :: Python :: 3.8
Classifier: Programming Language :: Python :: 3.9
Classifier: Programming Language :: Python :: 3.10
Classifier: Programming Language :: Python :: 3.11
Requires-Python: >=3.8
Requires-Dist: click
Requires-Dist: mrcfile
Requires-Dist: numpy
Requires-Dist: pandas
Requires-Dist: rich
Requires-Dist: scipy
Requires-Dist: sh
Provides-Extra: align-filament-particles
Requires-Dist: starfile; extra == 'align-filament-particles'
Provides-Extra: all
Requires-Dist: cryohub; extra == 'all'
Requires-Dist: cryotypes; extra == 'all'
Requires-Dist: edt; extra == 'all'
Requires-Dist: eulerangles; extra == 'all'
Requires-Dist: ipython; extra == 'all'
Requires-Dist: kaleido; extra == 'all'
Requires-Dist: magicgui; extra == 'all'
Requires-Dist: matplotlib; extra == 'all'
Requires-Dist: mdocfile; extra == 'all'
Requires-Dist: napari; extra == 'all'
Requires-Dist: napari[pyqt5]; extra == 'all'
Requires-Dist: plotly; extra == 'all'
Requires-Dist: scikit-image; extra == 'all'
Requires-Dist: starfile; extra == 'all'
Requires-Dist: tabulate; extra == 'all'
Provides-Extra: center-filament
Requires-Dist: scikit-image; extra == 'center-filament'
Provides-Extra: classify-densities
Requires-Dist: edt; extra == 'classify-densities'
Requires-Dist: matplotlib; extra == 'classify-densities'
Requires-Dist: plotly; extra == 'classify-densities'
Provides-Extra: create-mask
Requires-Dist: edt; extra == 'create-mask'
Provides-Extra: cryosparc
Requires-Dist: ipython; extra == 'cryosparc'
Requires-Dist: magicgui; extra == 'cryosparc'
Requires-Dist: plotly; extra == 'cryosparc'
Requires-Dist: starfile; extra == 'cryosparc'
Provides-Extra: csplot
Requires-Dist: ipython; extra == 'csplot'
Requires-Dist: magicgui; extra == 'csplot'
Requires-Dist: plotly; extra == 'csplot'
Provides-Extra: dev
Requires-Dist: black; extra == 'dev'
Requires-Dist: cryohub; extra == 'dev'
Requires-Dist: cryotypes; extra == 'dev'
Requires-Dist: edt; extra == 'dev'
Requires-Dist: eulerangles; extra == 'dev'
Requires-Dist: ipython; extra == 'dev'
Requires-Dist: kaleido; extra == 'dev'
Requires-Dist: magicgui; extra == 'dev'
Requires-Dist: matplotlib; extra == 'dev'
Requires-Dist: mdocfile; extra == 'dev'
Requires-Dist: napari; extra == 'dev'
Requires-Dist: napari[pyqt5]; extra == 'dev'
Requires-Dist: pdbpp; extra == 'dev'
Requires-Dist: plotly; extra == 'dev'
Requires-Dist: pre-commit; extra == 'dev'
Requires-Dist: rich; extra == 'dev'
Requires-Dist: ruff; extra == 'dev'
Requires-Dist: scikit-image; extra == 'dev'
Requires-Dist: starfile; extra == 'dev'
Requires-Dist: tabulate; extra == 'dev'
Provides-Extra: extract-z-snapshots
Requires-Dist: cryohub; extra == 'extract-z-snapshots'
Requires-Dist: cryotypes; extra == 'extract-z-snapshots'
Requires-Dist: napari[pyqt5]; extra == 'extract-z-snapshots'
Provides-Extra: fix-filament-ids
Requires-Dist: starfile; extra == 'fix-filament-ids'
Provides-Extra: fix-mdoc
Requires-Dist: mdocfile; extra == 'fix-mdoc'
Provides-Extra: flip-z
Requires-Dist: eulerangles; extra == 'flip-z'
Requires-Dist: starfile; extra == 'flip-z'
Provides-Extra: generate-tilt-angles
Requires-Dist: starfile; extra == 'generate-tilt-angles'
Provides-Extra: image
Requires-Dist: cryohub; extra == 'image'
Requires-Dist: cryotypes; extra == 'image'
Requires-Dist: edt; extra == 'image'
Requires-Dist: eulerangles; extra == 'image'
Requires-Dist: kaleido; extra == 'image'
Requires-Dist: matplotlib; extra == 'image'
Requires-Dist: napari; extra == 'image'
Requires-Dist: napari[pyqt5]; extra == 'image'
Requires-Dist: plotly; extra == 'image'
Requires-Dist: scikit-image; extra == 'image'
Requires-Dist: starfile; extra == 'image'
Provides-Extra: merge-star
Requires-Dist: starfile; extra == 'merge-star'
Provides-Extra: offset-angle
Requires-Dist: mdocfile; extra == 'offset-angle'
Provides-Extra: prepare-isonet
Requires-Dist: starfile; extra == 'prepare-isonet'
Provides-Extra: project-profile
Requires-Dist: kaleido; extra == 'project-profile'
Requires-Dist: napari; extra == 'project-profile'
Requires-Dist: plotly; extra == 'project-profile'
Provides-Extra: relion
Requires-Dist: starfile; extra == 'relion'
Provides-Extra: spoof-mdoc
Requires-Dist: mdocfile; extra == 'spoof-mdoc'
Provides-Extra: summarize
Requires-Dist: tabulate; extra == 'summarize'
Provides-Extra: warp
Requires-Dist: mdocfile; extra == 'warp'
Requires-Dist: starfile; extra == 'warp'
Requires-Dist: tabulate; extra == 'warp'
